setup.cfg
setup.py
pytpl/__init__.py
pytpl.egg-info/PKG-INFO
pytpl.egg-info/SOURCES.txt
pytpl.egg-info/dependency_links.txt
pytpl.egg-info/entry_points.txt
pytpl.egg-info/requires.txt
pytpl.egg-info/top_level.txt
pytpl.egg-info/zip-safe
pytpl/cli/__init__.py
pytpl/cli/pytpl.py
pytpl/extable/__init__.py
pytpl/extable/table.py
pytpl/tests/__init__.py
pytpl/tests/test_pytpl.py